LICENSE.txt
README.md
setup.py
utility_stella/__init__.py
utility_stella/__main__.py
utility_stella/log_config.py
utility_stella.egg-info/PKG-INFO
utility_stella.egg-info/SOURCES.txt
utility_stella.egg-info/dependency_links.txt
utility_stella.egg-info/requires.txt
utility_stella.egg-info/top_level.txt