Metadata-Version: 2.1
Name: utility-stella
Version: 0.0.2
Summary: utility per progetto stella 
Home-page: UNKNOWN
Author: Jorge figueroa
Author-email: atientas0412@gmail.com
License: MIT
Keywords: utility_stella
Platform: UNKNOWN
Classifier: Development Status :: 3 - Alpha
Classifier: Intended Audience :: Developers
Classifier: Topic :: Software Development :: Build Tools
Classifier: License :: OSI Approved :: MIT License
Classifier: Programming Language :: Python :: 3
License-File: LICENSE.txt
